[
  {
    "file": "dji_fly_20260321_181834_189_1774021582162_photo_overlay.jpg",
    "original": "dji_fly_20260321_181834_189_1774021582162_photo.jpg",
    "center_lat": 49.11022357,
    "center_lon": 11.68386843,
    "yaw": 46.0,
    "alt_agl": 72.9,
    "bounds": [
      [
        49.10964245,
        11.6829851
      ],
      [
        49.1108047,
        11.68475177
      ]
    ],
    "size_kb": 175
  },
  {
    "file": "dji_fly_20260321_181842_190_1774021581874_photo_overlay.jpg",
    "original": "dji_fly_20260321_181842_190_1774021581874_photo.jpg",
    "center_lat": 49.11034612,
    "center_lon": 11.68405946,
    "yaw": 46.1,
    "alt_agl": 67.9,
    "bounds": [
      [
        49.10980473,
        11.68323694
      ],
      [
        49.11088751,
        11.68488198
      ]
    ],
    "size_kb": 178
  },
  {
    "file": "dji_fly_20260321_181928_191_1774021581565_photo_overlay.jpg",
    "original": "dji_fly_20260321_181928_191_1774021581565_photo.jpg",
    "center_lat": 49.11010934,
    "center_lon": 11.68432358,
    "yaw": -44.8,
    "alt_agl": 117.8,
    "bounds": [
      [
        49.10917295,
        11.6828917
      ],
      [
        49.11104572,
        11.68575546
      ]
    ],
    "size_kb": 165
  },
  {
    "file": "dji_fly_20260321_182012_192_1774021581281_photo_overlay.jpg",
    "original": "dji_fly_20260321_182012_192_1774021581281_photo.jpg",
    "center_lat": 49.11006799,
    "center_lon": 11.68415358,
    "yaw": 44.5,
    "alt_agl": 97.5,
    "bounds": [
      [
        49.10929357,
        11.6829676
      ],
      [
        49.11084241,
        11.68533956
      ]
    ],
    "size_kb": 168
  },
  {
    "file": "dji_fly_20260321_182020_193_1774021581034_photo_overlay.jpg",
    "original": "dji_fly_20260321_182020_193_1774021581034_photo.jpg",
    "center_lat": 49.11029044,
    "center_lon": 11.68383276,
    "yaw": 46.9,
    "alt_agl": 97.6,
    "bounds": [
      [
        49.10951098,
        11.68265326
      ],
      [
        49.11106989,
        11.68501225
      ]
    ],
    "size_kb": 152
  },
  {
    "file": "dji_fly_20260321_182032_194_1774021580783_photo_overlay.jpg",
    "original": "dji_fly_20260321_182032_194_1774021580783_photo.jpg",
    "center_lat": 49.11029046,
    "center_lon": 11.68383276,
    "yaw": 138.1,
    "alt_agl": 97.7,
    "bounds": [
      [
        49.10952059,
        11.68263834
      ],
      [
        49.11106032,
        11.68502717
      ]
    ],
    "size_kb": 163
  },
  {
    "file": "dji_fly_20260321_182038_195_1774021580540_photo_overlay.jpg",
    "original": "dji_fly_20260321_182038_195_1774021580540_photo.jpg",
    "center_lat": 49.11029042,
    "center_lon": 11.68383444,
    "yaw": 129.1,
    "alt_agl": 85.5,
    "bounds": [
      [
        49.10960405,
        11.68281644
      ],
      [
        49.11097678,
        11.68485244
      ]
    ],
    "size_kb": 169
  },
  {
    "file": "dji_fly_20260321_182042_196_1774021580281_photo_overlay.jpg",
    "original": "dji_fly_20260321_182042_196_1774021580281_photo.jpg",
    "center_lat": 49.11029036,
    "center_lon": 11.68383393,
    "yaw": 46.2,
    "alt_agl": 85.4,
    "bounds": [
      [
        49.10960929,
        11.68279971
      ],
      [
        49.11097142,
        11.68486814
      ]
    ],
    "size_kb": 166
  }
]